nonebot_plugin_dice_narrator/__init__.py
nonebot_plugin_dice_narrator/config.py
nonebot_plugin_dice_narrator/matchers.py
nonebot_plugin_dice_narrator/narrator.py
nonebot_plugin_dice_narrator/utils/common.py
nonebot_plugin_dice_narrator/utils/message_parse.py
nonebot_plugin_dice_narrator/utils/openai_funcs.py
nonebot_plugin_dice_narrator-0.1.13.dist-info/LICENSE
nonebot_plugin_dice_narrator-0.1.13.dist-info/METADATA
nonebot_plugin_dice_narrator-0.1.13.dist-info/WHEEL
nonebot_plugin_dice_narrator-0.1.13.dist-info/entry_points.txt
nonebot_plugin_dice_narrator-0.1.13.dist-info/RECORD
