Metadata-Version: 2.1
Name: nonebot-plugin-dice-narrator
Version: 0.1.13
Summary: 一只可爱的AI掷骰姬
Home-page: https://github.com/KroMiose/nonebot-plugin-dice-narrator
Author: KroMiose
Author-email: li_xiangff@163.com
Requires-Python: >=3.9,<3.12
Classifier: Programming Language :: Python :: 3
Classifier: Programming Language :: Python :: 3.9
Classifier: Programming Language :: Python :: 3.10
Classifier: Programming Language :: Python :: 3.11
Requires-Dist: httpx (>=0.27.0,<0.28.0)
Requires-Dist: miose-toolkit-common (>=0.3.2,<0.4.0)
Requires-Dist: nonebot-adapter-onebot (>=2.4.2,<3.0.0)
Requires-Dist: nonebot2[fastapi] (>=2.2.1,<3.0.0)
Requires-Dist: openai (>=0.27.0)
Project-URL: Repository, https://github.com/KroMiose/nonebot-plugin-dice-narrator
